qiskit_emulator_helper/__init__.py
qiskit_emulator_helper/backends.py
qiskit_emulator_helper-0.1.2.dist-info/METADATA
qiskit_emulator_helper-0.1.2.dist-info/WHEEL
qiskit_emulator_helper-0.1.2.dist-info/top_level.txt
qiskit_emulator_helper-0.1.2.dist-info/RECORD
