Metadata-Version: 2.4
Name: qiskit-emulator-helper
Version: 0.1.2
Summary: A helper library to easily find, propose, and get Qiskit's fake backends (emulators).
Author-email: NT Nguyen <ntn9uy3n@gmail.com>
Classifier: Programming Language :: Python :: 3
Classifier: License :: OSI Approved :: MIT License
Classifier: Operating System :: OS Independent
Requires-Python: >=3.8
Requires-Dist: qiskit-ibm-runtime>=0.20.0
